iocextract.py
iocextract-1.16.1.dist-info/LICENSE
iocextract-1.16.1.dist-info/METADATA
iocextract-1.16.1.dist-info/WHEEL
iocextract-1.16.1.dist-info/entry_points.txt
iocextract-1.16.1.dist-info/top_level.txt
iocextract-1.16.1.dist-info/RECORD
